artific/__init__.py
artific/artific.py
artific/cli.py
artific-0.0.13.dist-info/AUTHORS.rst
artific-0.0.13.dist-info/LICENSE
artific-0.0.13.dist-info/METADATA
artific-0.0.13.dist-info/WHEEL
artific-0.0.13.dist-info/entry_points.txt
artific-0.0.13.dist-info/top_level.txt
artific-0.0.13.dist-info/RECORD
